LICENSE
MANIFEST.in
README.rst
pyproject.toml
setup.cfg
setup.py
django_html_generator.egg-info/PKG-INFO
django_html_generator.egg-info/SOURCES.txt
django_html_generator.egg-info/dependency_links.txt
django_html_generator.egg-info/requires.txt
django_html_generator.egg-info/top_level.txt
html_generator/__init__.py
html_generator/admin.py
html_generator/apps.py
html_generator/forms.py
html_generator/models.py
html_generator/tests.py
html_generator/urls.py
html_generator/views.py
html_generator/migrations/__init__.py